[
  {
    "id": 1,
    "brand": "OnePlus",
    "model": "6",
    "screen": "6.28",
    "resolution": "1080 x 2280",
    "build": "glass",
    "protection": "corning gorilla glass 5",
    "os": "android",
    "version": "8.1",
    "chipset": "qualcomm snapdragon 845",
    "gpu": "adreno 630",
    "memory": "8",
    "internal": "128",
    "camVariant": "dual",
    "cam1": "16",
    "cam2": "20",
    "frontCam": "12",
    "battery": "4000",
    "color": "red",
    "usbType": "type-c"
  },
  {
    "id": 2,
    "brand": "Samsung",
    "model": "S10",
    "screen": "6.1",
    "resolution": "1440 x 3040",
    "build": "glass",
    "protection": "corning gorilla glass 6",
    "os": "android",
    "version": "9.0",
    "chipset": "exynos 9820",
    "gpu": "mali g70",
    "memory": "8",
    "internal": "512",
    "camVariant": "triple",
    "cam1": "12",
    "cam2": "12",
    "cam3": "16",
    "frontCam": "10",
    "battery": "3400",
    "color": "black",
    "usbType": "type-c"
  }
]
